MANIFEST.in
setup.py
BwETAF/__init__.py
BwETAF/_errors.py
BwETAF/_utils.py
BwETAF/common_imports.py
BwETAF/independent.py
BwETAF/main.py
BwETAF.egg-info/PKG-INFO
BwETAF.egg-info/SOURCES.txt
BwETAF.egg-info/dependency_links.txt
BwETAF.egg-info/requires.txt
BwETAF.egg-info/top_level.txt
BwETAF/api/predict.py
BwETAF/api/predictv2.py
BwETAF/data/data_loader.py
BwETAF/data/data_low.py
BwETAF/data/data_processing.py
BwETAF/data/data_sorting.py
BwETAF/model/layers.py
BwETAF/model/model.py
BwETAF/sharding/main.py
BwETAF/tokenizer/main.py
BwETAF/trainerNeval/eval.py