Metadata-Version: 2.1
Name: BwETAF
Version: 0.6
Summary: Module to load BwETAF models (Flax)
Author: Boring._.wicked
Classifier: Programming Language :: Python :: 3
Classifier: License :: OSI Approved :: MIT License
